{
  "AbilityList": [
    {
      "Name": "LocalPlayer_CommonAbility_AttackBreak",
      "TargetInfo": {
        "TargetType": "Caster"
      },
      "OnStart": [
        {
          "$type": "RPG.GameCore.AddAdventureModifier",
          "TargetType": {
            "$type": "RPG.GameCore.TargetAlias",
            "Alias": "Caster"
          },
          "ModifierName": "ADV_StageAbility_MazeCommon_OnStageEffect"
        },
        {
          "$type": "RPG.GameCore.AddAdventureModifier",
          "TargetType": {
            "$type": "RPG.GameCore.TargetAlias",
            "Alias": "Caster"
          },
          "ModifierName": "ADV_StageAbility_MazeCommon_ListenEnterBattle_Common"
        },
        {
          "$type": "RPG.GameCore.PredicateTaskList",
          "Predicate": {
            "$type": "RPG.GameCore.ByCharacterDamageType",
            "TargetType": {
              "$type": "RPG.GameCore.TargetAlias",
              "Alias": "Caster"
            },
            "DamageType": "Physical"
          },
          "SuccessTaskList": [
            {
              "$type": "RPG.GameCore.AddAdventureModifier",
              "TargetType": {
                "$type": "RPG.GameCore.TargetAlias",
                "Alias": "Caster"
              },
              "ModifierName": "ADV_StageAbility_MazeCommon_ListenEnterBattle_Physical"
            }
          ]
        },
        {
          "$type": "RPG.GameCore.PredicateTaskList",
          "Predicate": {
            "$type": "RPG.GameCore.ByCharacterDamageType",
            "TargetType": {
              "$type": "RPG.GameCore.TargetAlias",
              "Alias": "Caster"
            },
            "DamageType": "Fire"
          },
          "SuccessTaskList": [
            {
              "$type": "RPG.GameCore.AddAdventureModifier",
              "TargetType": {
                "$type": "RPG.GameCore.TargetAlias",
                "Alias": "Caster"
              },
              "ModifierName": "ADV_StageAbility_MazeCommon_ListenEnterBattle_Fire"
            }
          ]
        },
        {
          "$type": "RPG.GameCore.PredicateTaskList",
          "Predicate": {
            "$type": "RPG.GameCore.ByCharacterDamageType",
            "TargetType": {
              "$type": "RPG.GameCore.TargetAlias",
              "Alias": "Caster"
            },
            "DamageType": "Ice"
          },
          "SuccessTaskList": [
            {
              "$type": "RPG.GameCore.AddAdventureModifier",
              "TargetType": {
                "$type": "RPG.GameCore.TargetAlias",
                "Alias": "Caster"
              },
              "ModifierName": "ADV_StageAbility_MazeCommon_ListenEnterBattle_Ice"
            }
          ]
        },
        {
          "$type": "RPG.GameCore.PredicateTaskList",
          "Predicate": {
            "$type": "RPG.GameCore.ByCharacterDamageType",
            "TargetType": {
              "$type": "RPG.GameCore.TargetAlias",
              "Alias": "Caster"
            },
            "DamageType": "Thunder"
          },
          "SuccessTaskList": [
            {
              "$type": "RPG.GameCore.AddAdventureModifier",
              "TargetType": {
                "$type": "RPG.GameCore.TargetAlias",
                "Alias": "Caster"
              },
              "ModifierName": "ADV_StageAbility_MazeCommon_ListenEnterBattle_Thunder"
            }
          ]
        },
        {
          "$type": "RPG.GameCore.PredicateTaskList",
          "Predicate": {
            "$type": "RPG.GameCore.ByCharacterDamageType",
            "TargetType": {
              "$type": "RPG.GameCore.TargetAlias",
              "Alias": "Caster"
            },
            "DamageType": "Wind"
          },
          "SuccessTaskList": [
            {
              "$type": "RPG.GameCore.AddAdventureModifier",
              "TargetType": {
                "$type": "RPG.GameCore.TargetAlias",
                "Alias": "Caster"
              },
              "ModifierName": "ADV_StageAbility_MazeCommon_ListenEnterBattle_Wind"
            }
          ]
        },
        {
          "$type": "RPG.GameCore.PredicateTaskList",
          "Predicate": {
            "$type": "RPG.GameCore.ByCharacterDamageType",
            "TargetType": {
              "$type": "RPG.GameCore.TargetAlias",
              "Alias": "Caster"
            },
            "DamageType": "Quantum"
          },
          "SuccessTaskList": [
            {
              "$type": "RPG.GameCore.AddAdventureModifier",
              "TargetType": {
                "$type": "RPG.GameCore.TargetAlias",
                "Alias": "Caster"
              },
              "ModifierName": "ADV_StageAbility_MazeCommon_ListenEnterBattle_Quantum"
            }
          ]
        },
        {
          "$type": "RPG.GameCore.PredicateTaskList",
          "Predicate": {
            "$type": "RPG.GameCore.ByCharacterDamageType",
            "TargetType": {
              "$type": "RPG.GameCore.TargetAlias",
              "Alias": "Caster"
            },
            "DamageType": "Imaginary"
          },
          "SuccessTaskList": [
            {
              "$type": "RPG.GameCore.AddAdventureModifier",
              "TargetType": {
                "$type": "RPG.GameCore.TargetAlias",
                "Alias": "Caster"
              },
              "ModifierName": "ADV_StageAbility_MazeCommon_ListenEnterBattle_Imaginary"
            }
          ]
        }
      ]
    },
    {
      "Name": "MazeMonster_CommonAbility_DisAdventage",
      "TargetInfo": {
        "TargetType": "Caster"
      },
      "OnStart": [
        {
          "$type": "RPG.GameCore.AddAdventureModifier",
          "TargetType": {
            "$type": "RPG.GameCore.TargetAlias",
            "Alias": "Caster"
          },
          "ModifierName": "ADV_StageAbility_MazeCommon_ListenEnterBattle_DisAdventage"
        }
      ]
    },
    {
      "Name": "MazeMonster_CommonAbility_Default",
      "TargetInfo": {
        "TargetType": "Caster"
      },
      "OnStart": []
    }
  ]
}