{
  "OnInitSequece": [
    {
      "TaskList": []
    }
  ],
  "OnStartSequece": [
    {
      "TaskList": [
        {
          "$type": "RPG.GameCore.LockPlayerControl"
        },
        {
          "$type": "RPG.GameCore.ShowTalkUI",
          "Show": true
        },
        {
          "$type": "RPG.GameCore.PlaySimpleTalk",
          "SimpleTalkList": [
            {}
          ]
        },
        {
          "$type": "RPG.GameCore.WaitSimpleTalkFinish"
        },
        {
          "$type": "RPG.GameCore.PlayOptionTalk",
          "OptionList": [
            {
              "OptionTextmapID": {
                "hash": 339453363
              },
              "OptionIconPath": "SpriteOutput/TalkIcon/ChatIcon.png",
              "TriggerCustomString": "EnterFloor_10101002"
            },
            {
              "OptionTextmapID": {
                "hash": 1905537304
              },
              "OptionIconPath": "SpriteOutput/TalkIcon/ChatIcon.png",
              "TriggerCustomString": "EnterFloor_10101003"
            },
            {
              "OptionTextmapID": {
                "hash": 1146022417
              },
              "OptionIconPath": "SpriteOutput/TalkIcon/ChatIcon.png",
              "TriggerCustomString": "EnterFloor_10101004"
            },
            {
              "OptionTextmapID": {
                "hash": 1723323179
              },
              "OptionIconPath": "SpriteOutput/TalkIcon/ChatIcon.png",
              "TriggerCustomString": "SwitchMap_Exit"
            }
          ]
        }
      ]
    },
    {
      "TaskList": [
        {
          "$type": "RPG.GameCore.WaitCustomString",
          "CustomString": "EnterFloor_10101002"
        },
        {
          "$type": "RPG.GameCore.ShowTalkUI"
        },
        {
          "$type": "RPG.GameCore.EnterFloor",
          "FloorID": 10101002
        }
      ]
    },
    {
      "TaskList": [
        {
          "$type": "RPG.GameCore.WaitCustomString",
          "CustomString": "EnterFloor_10101003"
        },
        {
          "$type": "RPG.GameCore.ShowTalkUI"
        },
        {
          "$type": "RPG.GameCore.EnterFloor",
          "FloorID": 10101003
        }
      ]
    },
    {
      "TaskList": [
        {
          "$type": "RPG.GameCore.WaitCustomString",
          "CustomString": "EnterFloor_10101004"
        },
        {
          "$type": "RPG.GameCore.ShowTalkUI"
        },
        {
          "$type": "RPG.GameCore.EnterFloor",
          "FloorID": 10101004
        }
      ]
    },
    {
      "TaskList": [
        {
          "$type": "RPG.GameCore.WaitCustomString",
          "CustomString": "SwitchMap_Exit"
        },
        {
          "$type": "RPG.GameCore.UnLockPlayerControl"
        },
        {
          "$type": "RPG.GameCore.ShowTalkUI"
        }
      ]
    }
  ]
}