{
  "OnInitSequece": [],
  "OnStartSequece": [
    {
      "TaskList": [
        {
          "$type": "RPG.GameCore.LevelStoryInitialize",
          "LockCamera": false,
          "EntityVisiableList": [],
          "CreateCharacterList": []
        },
        {
          "$type": "RPG.GameCore.AdvNpcFaceToPlayer",
          "GroupID": 3,
          "GroupNpcID": 400001
        },
        {
          "$type": "RPG.GameCore.PlaySimpleTalk",
          "SimpleTalkList": [
            {
              "VoiceID": 501024301
            },
            {
              "VoiceID": 501024302
            }
          ]
        },
        {
          "$type": "RPG.GameCore.WaitSimpleTalkFinish"
        },
        {
          "$type": "RPG.GameCore.PlayOptionTalk",
          "OptionList": [
            {
              "OptionTextmapID": {
                "hash": 892649333
              },
              "OptionIconPath": "SpriteOutput/TalkIcon/ChatIcon.png",
              "TriggerCustomString": "VoiceTalk_501024303"
            },
            {
              "OptionTextmapID": {
                "hash": 892649335
              },
              "OptionIconPath": "SpriteOutput/TalkIcon/ChatIcon.png",
              "TriggerCustomString": "VoiceTalk_501024305"
            }
          ]
        }
      ]
    },
    {
      "TaskList": [
        {
          "$type": "RPG.GameCore.WaitCustomString",
          "CustomString": "VoiceTalk_501024303"
        },
        {
          "$type": "RPG.GameCore.PlaySimpleTalk",
          "SimpleTalkList": [
            {
              "VoiceID": 501024304
            },
            {
              "VoiceID": 501024307
            }
          ]
        },
        {
          "$type": "RPG.GameCore.WaitSimpleTalkFinish"
        },
        {
          "$type": "RPG.GameCore.PlayOptionTalk",
          "OptionList": [
            {
              "OptionTextmapID": {
                "hash": 892649338
              },
              "OptionIconPath": "SpriteOutput/TalkIcon/ChatIcon.png",
              "TriggerCustomString": "VoiceTalk_501024308"
            },
            {
              "OptionTextmapID": {
                "hash": -1836234025
              },
              "OptionIconPath": "SpriteOutput/TalkIcon/ChatIcon.png",
              "TriggerCustomString": "VoiceTalk_501024310"
            }
          ]
        }
      ]
    },
    {
      "TaskList": [
        {
          "$type": "RPG.GameCore.WaitCustomString",
          "CustomString": "VoiceTalk_501024305"
        },
        {
          "$type": "RPG.GameCore.PlaySimpleTalk",
          "SimpleTalkList": [
            {
              "VoiceID": 501024306
            },
            {
              "VoiceID": 501024307
            }
          ]
        },
        {
          "$type": "RPG.GameCore.WaitSimpleTalkFinish"
        },
        {
          "$type": "RPG.GameCore.PlayOptionTalk",
          "OptionList": [
            {
              "OptionTextmapID": {
                "hash": 892649338
              },
              "OptionIconPath": "SpriteOutput/TalkIcon/ChatIcon.png",
              "TriggerCustomString": "VoiceTalk_501024308"
            },
            {
              "OptionTextmapID": {
                "hash": -1836234025
              },
              "OptionIconPath": "SpriteOutput/TalkIcon/ChatIcon.png",
              "TriggerCustomString": "VoiceTalk_501024310"
            }
          ]
        }
      ]
    },
    {
      "TaskList": [
        {
          "$type": "RPG.GameCore.WaitCustomString",
          "CustomString": "VoiceTalk_501024308"
        },
        {
          "$type": "RPG.GameCore.PlaySimpleTalk",
          "SimpleTalkList": [
            {
              "VoiceID": 501024309
            },
            {
              "VoiceID": 501024312
            }
          ]
        },
        {
          "$type": "RPG.GameCore.WaitSimpleTalkFinish"
        },
        {
          "$type": "RPG.GameCore.PlayOptionTalk",
          "OptionList": [
            {
              "OptionTextmapID": {
                "hash": -1836234022
              },
              "OptionIconPath": "SpriteOutput/TalkIcon/ChatIcon.png",
              "TriggerCustomString": "VoiceTalk_501024313"
            },
            {
              "OptionTextmapID": {
                "hash": -1836234017
              },
              "OptionIconPath": "SpriteOutput/TalkIcon/ChatIcon.png",
              "TriggerCustomString": "VoiceTalk_501024318"
            },
            {
              "OptionTextmapID": {
                "hash": 2055448753
              },
              "OptionIconPath": "SpriteOutput/TalkIcon/ChatIcon.png",
              "TriggerCustomString": "VoiceTalk_501024329"
            }
          ]
        }
      ]
    },
    {
      "TaskList": [
        {
          "$type": "RPG.GameCore.WaitCustomString",
          "CustomString": "VoiceTalk_501024310"
        },
        {
          "$type": "RPG.GameCore.PlaySimpleTalk",
          "SimpleTalkList": [
            {
              "VoiceID": 501024311
            },
            {
              "VoiceID": 501024312
            }
          ]
        },
        {
          "$type": "RPG.GameCore.WaitSimpleTalkFinish"
        },
        {
          "$type": "RPG.GameCore.PlayOptionTalk",
          "OptionList": [
            {
              "OptionTextmapID": {
                "hash": -1836234022
              },
              "OptionIconPath": "SpriteOutput/TalkIcon/ChatIcon.png",
              "TriggerCustomString": "VoiceTalk_501024313"
            },
            {
              "OptionTextmapID": {
                "hash": -1836234017
              },
              "OptionIconPath": "SpriteOutput/TalkIcon/ChatIcon.png",
              "TriggerCustomString": "VoiceTalk_501024318"
            },
            {
              "OptionTextmapID": {
                "hash": 2055448753
              },
              "OptionIconPath": "SpriteOutput/TalkIcon/ChatIcon.png",
              "TriggerCustomString": "VoiceTalk_501024329"
            }
          ]
        }
      ]
    },
    {
      "TaskList": [
        {
          "$type": "RPG.GameCore.WaitCustomString",
          "CustomString": "VoiceTalk_501024313"
        },
        {
          "$type": "RPG.GameCore.PlaySimpleTalk",
          "SimpleTalkList": [
            {
              "VoiceID": 501024314
            }
          ]
        },
        {
          "$type": "RPG.GameCore.WaitSimpleTalkFinish"
        },
        {
          "$type": "RPG.GameCore.PlayOptionTalk",
          "OptionList": [
            {
              "OptionTextmapID": {
                "hash": -1836234020
              },
              "OptionIconPath": "SpriteOutput/TalkIcon/ChatIcon.png",
              "TriggerCustomString": "VoiceTalk_501024315"
            },
            {
              "OptionTextmapID": {
                "hash": -1836234018
              },
              "OptionIconPath": "SpriteOutput/TalkIcon/ChatIcon.png",
              "TriggerCustomString": "VoiceTalk_501024329"
            }
          ]
        }
      ]
    },
    {
      "TaskList": [
        {
          "$type": "RPG.GameCore.WaitCustomString",
          "CustomString": "VoiceTalk_501024315"
        },
        {
          "$type": "RPG.GameCore.PlaySimpleTalk",
          "SimpleTalkList": [
            {
              "VoiceID": 501024316
            }
          ]
        },
        {
          "$type": "RPG.GameCore.WaitSimpleTalkFinish"
        },
        {
          "$type": "RPG.GameCore.EndStory"
        }
      ]
    },
    {
      "TaskList": [
        {
          "$type": "RPG.GameCore.WaitCustomString",
          "CustomString": "VoiceTalk_501024318"
        },
        {
          "$type": "RPG.GameCore.PlaySimpleTalk",
          "SimpleTalkList": [
            {
              "VoiceID": 501024319
            }
          ]
        },
        {
          "$type": "RPG.GameCore.WaitSimpleTalkFinish"
        },
        {
          "$type": "RPG.GameCore.TriggerCustomString",
          "CustomString": {
            "Value": "loop_501024301_1"
          }
        }
      ]
    },
    {
      "IsLoop": true,
      "TaskList": [
        {
          "$type": "RPG.GameCore.WaitCustomString",
          "CustomString": "loop_501024301_1"
        },
        {
          "$type": "RPG.GameCore.PlayOptionTalk",
          "OptionList": [
            {
              "OptionTextmapID": {
                "hash": 2055448744
              },
              "OptionIconPath": "SpriteOutput/TalkIcon/ChatIcon.png",
              "TriggerCustomString": "VoiceTalk_501024320"
            },
            {
              "OptionTextmapID": {
                "hash": 2055448746
              },
              "OptionIconPath": "SpriteOutput/TalkIcon/ChatIcon.png",
              "TriggerCustomString": "VoiceTalk_501024322"
            },
            {
              "OptionTextmapID": {
                "hash": 2055448748
              },
              "OptionIconPath": "SpriteOutput/TalkIcon/ChatIcon.png",
              "TriggerCustomString": "VoiceTalk_501024324"
            },
            {
              "OptionTextmapID": {
                "hash": 2055448750
              },
              "OptionIconPath": "SpriteOutput/TalkIcon/ChatIcon.png",
              "TriggerCustomString": "VoiceTalk_501024326"
            },
            {
              "OptionTextmapID": {
                "hash": 2055448752
              },
              "OptionIconPath": "SpriteOutput/TalkIcon/ChatContinueIcon.png",
              "TriggerCustomString": "VoiceTalk_501024329"
            }
          ],
          "HideSelected": true
        }
      ]
    },
    {
      "IsLoop": true,
      "TaskList": [
        {
          "$type": "RPG.GameCore.WaitCustomString",
          "CustomString": "VoiceTalk_501024320"
        },
        {
          "$type": "RPG.GameCore.PlaySimpleTalk",
          "SimpleTalkList": [
            {
              "VoiceID": 501024321
            }
          ]
        },
        {
          "$type": "RPG.GameCore.WaitSimpleTalkFinish"
        },
        {
          "$type": "RPG.GameCore.TriggerCustomString",
          "CustomString": {
            "Value": "loop_501024301_1"
          }
        }
      ]
    },
    {
      "IsLoop": true,
      "TaskList": [
        {
          "$type": "RPG.GameCore.WaitCustomString",
          "CustomString": "VoiceTalk_501024322"
        },
        {
          "$type": "RPG.GameCore.PlaySimpleTalk",
          "SimpleTalkList": [
            {
              "VoiceID": 501024323
            }
          ]
        },
        {
          "$type": "RPG.GameCore.WaitSimpleTalkFinish"
        },
        {
          "$type": "RPG.GameCore.TriggerCustomString",
          "CustomString": {
            "Value": "loop_501024301_1"
          }
        }
      ]
    },
    {
      "IsLoop": true,
      "TaskList": [
        {
          "$type": "RPG.GameCore.WaitCustomString",
          "CustomString": "VoiceTalk_501024324"
        },
        {
          "$type": "RPG.GameCore.PlaySimpleTalk",
          "SimpleTalkList": [
            {
              "VoiceID": 501024325
            }
          ]
        },
        {
          "$type": "RPG.GameCore.WaitSimpleTalkFinish"
        },
        {
          "$type": "RPG.GameCore.TriggerCustomString",
          "CustomString": {
            "Value": "loop_501024301_1"
          }
        }
      ]
    },
    {
      "IsLoop": true,
      "TaskList": [
        {
          "$type": "RPG.GameCore.WaitCustomString",
          "CustomString": "VoiceTalk_501024326"
        },
        {
          "$type": "RPG.GameCore.PlaySimpleTalk",
          "SimpleTalkList": [
            {
              "VoiceID": 501024327
            }
          ]
        },
        {
          "$type": "RPG.GameCore.WaitSimpleTalkFinish"
        },
        {
          "$type": "RPG.GameCore.TriggerCustomString",
          "CustomString": {
            "Value": "loop_501024301_1"
          }
        }
      ]
    },
    {
      "TaskList": [
        {
          "$type": "RPG.GameCore.WaitCustomString",
          "CustomString": "VoiceTalk_501024329"
        },
        {
          "$type": "RPG.GameCore.EndStory"
        }
      ]
    },
    {
      "TaskList": [
        {
          "$type": "RPG.GameCore.WaitStoryEnd"
        },
        {
          "$type": "RPG.GameCore.FinishLevelGraph"
        }
      ]
    }
  ]
}