{
  "OnInitSequece": [],
  "OnStartSequece": [
    {
      "IsLoop": true,
      "TaskList": [
        {
          "$type": "RPG.GameCore.WaitCustomString",
          "CustomString": "Act_20107010210"
        },
        {
          "$type": "RPG.GameCore.ResetBillboardInfo",
          "TargetCharacterType": "NPC",
          "ID": 400001,
          "GroupID": 20
        },
        {
          "$type": "RPG.GameCore.FinishStoryMission",
          "Key": "Mission_201070102"
        }
      ]
    },
    {
      "TaskList": [
        {
          "$type": "RPG.GameCore.SetBillboardInfo",
          "TargetCharacterType": "NPC",
          "ID": 400001,
          "GroupID": 20,
          "Name": {
            "hash": -1695397715
          },
          "MapIconType": 12
        }
      ]
    },
    {
      "IsLoop": true,
      "TaskList": [
        {
          "$type": "RPG.GameCore.WaitCustomString",
          "CustomString": "Talk_20107010201"
        },
        {
          "$type": "RPG.GameCore.TriggerStory",
          "StoryID": 201070102
        }
      ]
    }
  ]
}