[
  {
    "MaxPlayerLevel": 15,
    "LevelUpMission": 4010101,
    "Breaktips1": {
      "hash": -1689771034
    },
    "Breaktips2": {
      "hash": -2093055561
    },
    "LevelUpMissionTips": {
      "hash": -1571616738
    }
  },
  {
    "Level": 1,
    "MaxPlayerLevel": 20,
    "LevelUpMission": 4010102,
    "Breaktips1": {
      "hash": -1689771034
    },
    "Breaktips2": {
      "hash": -2093055561
    },
    "LevelUpMissionTips": {
      "hash": -1571616738
    }
  },
  {
    "Level": 2,
    "MaxPlayerLevel": 25,
    "LevelUpMission": 4010103,
    "Breaktips1": {
      "hash": -1689771034
    },
    "Breaktips2": {
      "hash": -2093055561
    },
    "LevelUpMissionTips": {
      "hash": -1571616738
    }
  },
  {
    "Level": 3,
    "MaxPlayerLevel": 30,
    "Breaktips1": {
      "hash": 371857150
    },
    "Breaktips2": {
      "hash": 371857150
    },
    "LevelUpMissionTips": {
      "hash": 371857150
    }
  }
]