{
  "OnInitSequece": [],
  "OnStartSequece": [
    {
      "TaskList": [
        {
          "$type": "RPG.GameCore.SelectorConfig",
          "TaskList": [
            {
              "$type": "RPG.GameCore.PropStateExecute",
              "TargetIsOwner": true,
              "Execute": [
                {
                  "$type": "RPG.GameCore.LockPlayerControl"
                },
                {
                  "$type": "RPG.GameCore.EnableNPCMonsterAI",
                  "GroupMonsterIDs": [],
                  "UniqueNames": []
                },
                {
                  "$type": "RPG.GameCore.TriggerMazeBuffSelect",
                  "BuffList": [
                    {
                      "BuffID": 5001171
                    },
                    {
                      "BuffID": 5001172
                    }
                  ],
                  "CustomStringList": [
                    "Maze_Prop_ChallengeBuffSelect_5001171",
                    "Maze_Prop_ChallengeBuffSelect_5001172"
                  ]
                }
              ]
            },
            {
              "$type": "RPG.GameCore.PropStateExecute",
              "TargetIsOwner": true,
              "Execute": [
                {
                  "$type": "RPG.GameCore.FinishLevelGraph"
                }
              ],
              "State": "Open"
            }
          ]
        }
      ]
    },
    {
      "TaskList": [
        {
          "$type": "RPG.GameCore.WaitCustomString",
          "CustomString": "Maze_Prop_ChallengeBuffSelect_5001171",
          "WaitOwnerOnly": true,
          "Sync": true
        },
        {
          "$type": "RPG.GameCore.AddMazeBuff",
          "TargetType": {
            "$type": "RPG.GameCore.TargetAlias",
            "Alias": "LightTeamEntity"
          },
          "ID": 5001171
        },
        {
          "$type": "RPG.GameCore.ChangeChallengeBuff",
          "BuffID": [
            5001171
          ]
        },
        {
          "$type": "RPG.GameCore.TriggerCustomString",
          "CustomString": {
            "Value": "Maze_Prop_ChallengeBuffSelectFinish_5001170"
          }
        }
      ]
    },
    {
      "TaskList": [
        {
          "$type": "RPG.GameCore.WaitCustomString",
          "CustomString": "Maze_Prop_ChallengeBuffSelect_5001172",
          "WaitOwnerOnly": true,
          "Sync": true
        },
        {
          "$type": "RPG.GameCore.AddMazeBuff",
          "TargetType": {
            "$type": "RPG.GameCore.TargetAlias",
            "Alias": "LightTeamEntity"
          },
          "ID": 5001172
        },
        {
          "$type": "RPG.GameCore.ChangeChallengeBuff",
          "BuffID": [
            5001172
          ]
        },
        {
          "$type": "RPG.GameCore.TriggerCustomString",
          "CustomString": {
            "Value": "Maze_Prop_ChallengeBuffSelectFinish_5001170"
          }
        }
      ]
    },
    {
      "TaskList": [
        {
          "$type": "RPG.GameCore.WaitCustomString",
          "CustomString": "Maze_Prop_ChallengeBuffSelectFinish_5001170"
        },
        {
          "$type": "RPG.GameCore.UnLockPlayerControl"
        },
        {
          "$type": "RPG.GameCore.EnableNPCMonsterAI",
          "Enable": true,
          "GroupMonsterIDs": [],
          "UniqueNames": []
        },
        {
          "$type": "RPG.GameCore.PropReqInteract",
          "TargetIsOwner": true,
          "InteractID": 1010
        },
        {
          "$type": "RPG.GameCore.ToastPage",
          "MessageOne": {
            "hash": -638479960
          },
          "MessageTwo": {
            "hash": 1750546642
          }
        },
        {
          "$type": "RPG.GameCore.FinishLevelGraph"
        }
      ]
    }
  ]
}